dataimport_aicare/__init__.py
dataimport_aicare/data_loading.py
dataimport_aicare/data_preprocessing.py
dataimport_aicare/generate_extra_columns.py
dataimport_aicare/minimal_config.yaml
dataimport_aicare-0.1.3.dist-info/METADATA
dataimport_aicare-0.1.3.dist-info/WHEEL
dataimport_aicare-0.1.3.dist-info/entry_points.txt
dataimport_aicare-0.1.3.dist-info/licenses/LICENSE
dataimport_aicare-0.1.3.dist-info/RECORD
